aaa.py
aaa_approx-1.0.2.dist-info/METADATA
aaa_approx-1.0.2.dist-info/RECORD
aaa_approx-1.0.2.dist-info/WHEEL
aaa_approx-1.0.2.dist-info/top_level.txt
