Metadata-Version: 2.1
Name: aaa-approx
Version: 1.0.2
Summary: A Python implementation of the AAA algorithm for rational approximation
Home-page: https://github.com/c-f-h/aaa
Author: Clemens Hofreither
Author-email: chofreither@numa.uni-linz.ac.at
License: UNKNOWN
Platform: UNKNOWN
Classifier: Programming Language :: Python :: 2.7
Classifier: Programming Language :: Python :: 3
Classifier: Intended Audience :: Science/Research
Classifier: Topic :: Scientific/Engineering :: Mathematics
Classifier: License :: OSI Approved :: BSD License
Requires-Dist: numpy (>=1.11)
Requires-Dist: scipy
